git_outlier/__init__.py
git_outlier/git_outlier.py
git_outlier-0.0.2.dist-info/LICENSE
git_outlier-0.0.2.dist-info/METADATA
git_outlier-0.0.2.dist-info/WHEEL
git_outlier-0.0.2.dist-info/entry_points.txt
git_outlier-0.0.2.dist-info/top_level.txt
git_outlier-0.0.2.dist-info/RECORD
