Metadata-Version: 2.1
Name: git-outlier
Version: 0.0.2
Summary: Data-driven screening to find source code that need refactoring
Home-page: https://github.com/BjrnJhsn/git-outlier
Author: Björn Johansson
Author-email: bjorn.ki.johansson@gmail.com
License: UNKNOWN
Project-URL: Bug Tracker, https://github.com/BjrnJhsn/git-outlier/issues
Platform: UNKNOWN
Classifier: Programming Language :: Python :: 3
Classifier: License :: OSI Approved :: GNU General Public License v3 (GPLv3)
Classifier: Operating System :: OS Independent
Classifier: Development Status :: 3 - Alpha
Classifier: Topic :: Software Development :: Version Control :: Git
Classifier: Topic :: Software Development
Requires-Python: >=3.6
License-File: LICENSE
Requires-Dist: python-dateutil
Requires-Dist: lizard (>=1.17.7)
